flexeval/__init__.py
flexeval/core/__init__.py
flexeval/core/chat_dataset/__init__.py
flexeval/core/chat_dataset/base.py
flexeval/core/chat_dataset/chatbot_bench.py
flexeval/core/chat_dataset/chatbot_bench_datasets/README.md
flexeval/core/chat_dataset/chatbot_bench_datasets/mt-en-ref-gpt4.jsonl
flexeval/core/chat_dataset/chatbot_bench_datasets/mt-en.jsonl
flexeval/core/chat_dataset/chatbot_bench_datasets/mt-ja-ref-gpt4.jsonl
flexeval/core/chat_dataset/chatbot_bench_datasets/mt-ja-ref-gpt4o-with-human-annotation.jsonl
flexeval/core/chat_dataset/chatbot_bench_datasets/mt-ja.jsonl
flexeval/core/chat_dataset/chatbot_bench_datasets/rakuda-v2-ja.jsonl
flexeval/core/chat_dataset/chatbot_bench_datasets/vicuna-en-ref-gpt4.jsonl
flexeval/core/chat_dataset/chatbot_bench_datasets/vicuna-en.jsonl
flexeval/core/chat_dataset/chatbot_bench_datasets/vicuna-ja-ref-gpt4.jsonl
flexeval/core/chat_dataset/chatbot_bench_datasets/vicuna-ja.jsonl
flexeval/core/chat_dataset/openai_messages.py
flexeval/core/chat_dataset/sacrebleu_dataset.py
flexeval/core/chat_dataset/template_based.py
flexeval/core/eval_setups.py
flexeval/core/evaluate_chat_response.py
flexeval/core/evaluate_from_data.py
flexeval/core/evaluate_generation.py
flexeval/core/evaluate_multiple_choice.py
flexeval/core/evaluate_pairwise.py
flexeval/core/evaluate_perplexity.py
flexeval/core/evaluate_reward_model.py
flexeval/core/few_shot_generator/__init__.py
flexeval/core/few_shot_generator/balanced.py
flexeval/core/few_shot_generator/base.py
flexeval/core/few_shot_generator/fixed.py
flexeval/core/few_shot_generator/rand.py
flexeval/core/generation_dataset/__init__.py
flexeval/core/generation_dataset/base.py
flexeval/core/generation_dataset/sacrebleu_dataset.py
flexeval/core/generation_dataset/template_based.py
flexeval/core/language_model/__init__.py
flexeval/core/language_model/base.py
flexeval/core/language_model/hf_lm.py
flexeval/core/language_model/litellm_api.py
flexeval/core/language_model/openai_api.py
flexeval-0.15.4.dist-info/METADATA
flexeval-0.15.4.dist-info/WHEEL
flexeval-0.15.4.dist-info/entry_points.txt
flexeval-0.15.4.dist-info/licenses/LICENSE
flexeval-0.15.4.dist-info/RECORD
