Metadata-Version: 2.4
Name: flexeval
Version: 0.15.4
Summary: 
License-File: LICENSE
Author: ryokan-ri
Author-email: ryokan.ri@sbintuitions.co.jp
Requires-Python: >=3.10,<3.13
Classifier: Programming Language :: Python :: 3
Classifier: Programming Language :: Python :: 3.10
Classifier: Programming Language :: Python :: 3.11
Classifier: Programming Language :: Python :: 3.12
Provides-Extra: vllm
Provides-Extra: wandb
Requires-Dist: datasets (>=2.14.6,<3.0.0)
Requires-Dist: evaluate (>=0.4.1,<0.5.0)
Requires-Dist: fuzzywuzzy (>=0.18.0,<0.19.0)
Requires-Dist: google-api-python-client (>=2.131.0,<3.0.0)
Requires-Dist: jinja2 (>=3.1.2,<4.0.0)
Requires-Dist: jiwer (>=3.0.4,<4.0.0)
Requires-Dist: jsonargparse[jsonnet] (>=4.26.1,<5.0.0)
Requires-Dist: litellm (>=1.52.9,<2.0.0)
Requires-Dist: loguru (>=0.7.2,<0.8.0)
Requires-Dist: math-verify[antlr4-13-2] (>=0.7.0,<0.8.0)
Requires-Dist: openai (>=1.52.2,<2.0.0)
Requires-Dist: peft (>=0.10.0,<0.11.0)
Requires-Dist: pyarrow (==16.1.0)
Requires-Dist: python-levenshtein (>=0.23.0,<0.24.0)
Requires-Dist: rouge (>=1.0.1,<2.0.0)
Requires-Dist: sacrebleu[ja] (>=2.4.1,<3.0.0)
Requires-Dist: scikit-learn (==1.6.1)
Requires-Dist: scipy (>=1.13.0,<2.0.0)
Requires-Dist: smart-open (>=7.1.0,<8.0.0)
Requires-Dist: sudachipy (>=0.6.10)
Requires-Dist: tiktoken (>=0.9.0,<0.10.0)
Requires-Dist: transformers[ja,sentencepiece,torch] (>=4.34.1,<5.0.0)
Requires-Dist: vllm (==0.10.2) ; extra == "vllm"
Requires-Dist: wandb (>=0.17.2,<0.18.0) ; extra == "wandb"
